{
    "name": "PHI-CL",
    "version": "3.0.0",
    "factorio_version": "2.0",
    "date": "2024-10-16",
    "title": "Phidias Collection",
    "author": "PHIDIAS0303",
    "contributers": "",
    "homepage": "",
    "description": "Additional compound entities and items to reduce the space needed\nSuch as better solar panel, accumulator\nAnd other feature such as water pump placement anywhere, large range radar, trash chest and pipe, passive power void, linked chest, empty world generation",
    "dependencies": [
        "base >= 2.0.0",
        "? space-age",
        "? quality >= 2.0.0",
        "? elevated-rails > 2.0.0"
    ]
}